FocusRecorder/FocusRecorder.py
FocusRecorder/__init__.py
FocusRecorder/command.py
FocusRecorder/default.py
FocusRecorder/init.py
FocusRecorder/overview.py
FocusRecorder/record.py
FocusRecorder/status.py
FocusRecorder/tags.py
FocusRecorder/title.py
FocusRecorder/utls.py
FocusRecorder-1.2.3.dist-info/LICENSE
FocusRecorder-1.2.3.dist-info/METADATA
FocusRecorder-1.2.3.dist-info/WHEEL
FocusRecorder-1.2.3.dist-info/entry_points.txt
FocusRecorder-1.2.3.dist-info/top_level.txt
FocusRecorder-1.2.3.dist-info/RECORD
