Metadata-Version: 2.1
Name: FocusRecorder
Version: 1.2.3
Summary: 记录电脑各应用使用记录
Home-page: https://github.com/Czile-create/FocusRecorder
Author: Czile
Author-email: Czile@foxmail.com
License: Apache License
Platform: UNKNOWN
Classifier: Programming Language :: Python :: 3
Classifier: License :: OSI Approved :: Apache Software License
Requires-Dist: prettytable (==3.3.0)
Requires-Dist: psutil (==5.9.0)
Requires-Dist: PyGetWindow (==0.0.9)
Requires-Dist: pywin32 (==303)
Requires-Dist: rich (==12.4.4)
